pipedrive/__init__.py
pipedrive-0.2.0.dist-info/METADATA
pipedrive-0.2.0.dist-info/WHEEL
pipedrive-0.2.0.dist-info/top_level.txt
pipedrive-0.2.0.dist-info/RECORD
